<?xml version="1.0" encoding="utf-8" ?>
<dwsync>
<file name="thumb.png" server="C:/xampp/htdocs/local/portfolio/" local="129977792647806859" remote="129977792640000000" Dst="0" />
<file name="thumb.png" server="C:/xampp/htdocs/local/www.olivercastelblanco.com/" local="130109729316289080" remote="130109729310000000" Dst="0" />
<file name="desc.json" server="C:/xampp/htdocs/local/www.olivercastelblanco.com/" local="130109772889741339" remote="130109772880000000" Dst="0" />
<file name="Screen01.jpg" server="C:/xampp/htdocs/local/www.olivercastelblanco.com/" local="130109726772323573" remote="130109726770000000" Dst="0" />
<file name="Screen02.jpg" server="C:/xampp/htdocs/local/www.olivercastelblanco.com/" local="130109726916081796" remote="130109726910000000" Dst="0" />
<file name="Screen03.jpg" server="C:/xampp/htdocs/local/www.olivercastelblanco.com/" local="130109727261491552" remote="130109727260000000" Dst="0" />
<file name="Screen04.jpg" server="C:/xampp/htdocs/local/www.olivercastelblanco.com/" local="130109728004874071" remote="130109728000000000" Dst="0" />
<file name="Screen05.jpg" server="C:/xampp/htdocs/local/www.olivercastelblanco.com/" local="130109727786171562" remote="130109727780000000" Dst="0" />
<file name="thumb-75.png" server="C:/xampp/htdocs/local/www.olivercastelblanco.com/" local="130109729344430689" remote="130109729340000000" Dst="0" />
</dwsync>